README.md
setup.py
url2features/__init__.py
url2features/cli.py
url2features/config.py
url2features/dns.py
url2features/featurize.py
url2features/file.py
url2features/host.py
url2features/params.py
url2features/path.py
url2features/pipeline.py
url2features/process.py
url2features/protocol.py
url2features/registration.py
url2features/simple.py
url2features/suffixes.py
url2features/tld.py
url2features.egg-info/PKG-INFO
url2features.egg-info/SOURCES.txt
url2features.egg-info/dependency_links.txt
url2features.egg-info/entry_points.txt
url2features.egg-info/requires.txt
url2features.egg-info/top_level.txt