Metadata-Version: 2.1
Name: url2features
Version: 0.2.0
Summary: Python command line application to extract features from a column of URLs inside a CSV or TSV dataset.
Home-page: http://getting-data-science-done.com
Author: John Hawkins
Author-email: johnc@getting-data-science-done.com
License: MIT
Project-URL: Documentation, http://url2features.readthedocs.io
Project-URL: Source, https://github.com/getting-data-science-done/url2features
Project-URL: Tracker, https://github.com/getting-data-science-done/url2features/issues
Platform: UNKNOWN
